fava_plugins/__init__.py
fava_plugins/split_income.py
fava_plugins/todo_as_error.py
fava_plugins-1.2.dist-info/licenses/LICENSE
fava_plugins-1.2.dist-info/METADATA
fava_plugins-1.2.dist-info/WHEEL
fava_plugins-1.2.dist-info/top_level.txt
fava_plugins-1.2.dist-info/RECORD
