Metadata-Version: 2.4
Name: fava-plugins
Version: 1.2
Summary: A collection of Beancount plugins.
Author-email: Jakob Schnitzer <mail@jakobschnitzer.de>
License-Expression: MIT
Project-URL: Homepage, https://github.com/beancount/fava-plugins
Project-URL: Source, https://github.com/beancount/fava-plugins
Project-URL: Issues, https://github.com/beancount/fava-plugins/issues
Keywords: fava,beancount,accounting
Classifier: Development Status :: 5 - Production/Stable
Classifier: Intended Audience :: Education
Classifier: Intended Audience :: End Users/Desktop
Classifier: Intended Audience :: Financial and Insurance Industry
Classifier: Intended Audience :: Information Technology
Classifier: Natural Language :: English
Classifier: Programming Language :: Python :: 3 :: Only
Classifier: Programming Language :: Python :: 3.10
Classifier: Programming Language :: Python :: 3.11
Classifier: Programming Language :: Python :: 3.12
Classifier: Programming Language :: Python :: 3.13
Classifier: Programming Language :: Python :: 3.14
Classifier: Topic :: Office/Business :: Financial :: Accounting
Classifier: Topic :: Office/Business :: Financial :: Investment
Requires-Python: >=3.10
License-File: LICENSE
Requires-Dist: beancount<4,>=2
Dynamic: license-file
